pytds_md5/__init__.py
pytds_md5/_generated.py
pytds_md5/collate.py
pytds_md5/extensions.py
pytds_md5/lcid.py
pytds_md5/login.py
pytds_md5/smp.py
pytds_md5/sspi.py
pytds_md5/tds.py
pytds_md5/tds_base.py
pytds_md5/tds_types.py
pytds_md5/tls.py
pytds_md5/tz.py
pytds_md5-0.0.2.dist-info/LICENSE
pytds_md5-0.0.2.dist-info/METADATA
pytds_md5-0.0.2.dist-info/WHEEL
pytds_md5-0.0.2.dist-info/top_level.txt
pytds_md5-0.0.2.dist-info/RECORD
